README.txt
setup.cfg
setup.py
type_constraint.py
type_constraint.egg-info/PKG-INFO
type_constraint.egg-info/SOURCES.txt
type_constraint.egg-info/dependency_links.txt
type_constraint.egg-info/top_level.txt