Metadata-Version: 1.0
Name: type_constraint
Version: 0.0.10
Summary: a type constraint tool for python function
Home-page: http://tieba.baidu.com/f?ie=utf-8&kw=%E5%91%A8%E4%BA%95%E6%B1%9F
Author: timchow
Author-email: jingjiang@staff.sina.com.cn
License: LGPL
Keywords: type constraint
Platform: UNKNOWN
